Workbook

Sheet CCS data
A1: Technology | B1: Dispachable | C1: Nominal investment (*total) [MEUR/MW_e] | D1: Nominal investment (*total) [MEUR/MW_e/m] | E1: Variable O&M (*total) [EUR/MWh_e] | F1: Fixed O&M (*total) [EUR/MW_e/y] | G1: Fixed O&M (*total) [EUR/MW_e/y/m] | H1: Year
A2: CCS | B2: 1 | C2: =plants!P6120 -> 0.090291697 | D2: =plants!O6120 -> 3.7112763e-07 | E2: =plants!H6120 -> 6.1551039 | F2: =plants!I6120 -> 78015.04 | G2: =plants!J6120 -> 0.012265588 | H2: 2030

Sheet plants
A1: name | B1: company | C1: street | D1: postcode | E1: city | F1: country | G1: capacity | H1: energy_source | I1: technology | K1: chp | L1: commissioned | M1: type | N1: lat | P1: lon | Q1: eic_code | R1: energy_source_level_1 | S1: energy_source_level_2 | T1: energy_source_level_3 | U1: additional_info | V1: comment | W1: source
A2: Marcinelle Energie (Carsid) | B2: DIRECT ENERGIE | F2: BE | G2: 413 | H2: Natural gas | I2: Combined cycle | N2: 50.41396 | P2: 4.40645 | Q2: 22WMARCIN000179H | R2: Fossil fuels | S2: Natural gas | W2: https://www.elia.be/en/grid-data/power-generation/generating-facilities#
A3: Aalst Syral GT | B3: Electrabel | F3: BE | G3: 43 | H3: Natural gas | I3: Gas turbine | K3: Yes | M3: CHP/IPP | R3: Fossil fuels | S3: Natural gas | W3: https://www.elia.be/en/grid-data/power-generation/generating-facilities#
A4: Aalst Syral ST | B4: Electrabel | F4: BE | G4: 5 | H4: Natural gas | I4: Steam turbine | K4: Yes | M4: CHP/IPP | R4: Fossil fuels | S4: Natural gas | W4: https://www.elia.be/en/grid-data/power-generation/generating-facilities#
A5: AALTER TJ | B5: Electrabel | F5: BE | G5: 18 | H5: Oil | I5: Gas turbine | R5: Fossil fuels | S5: Oil | W5: https://www.elia.be/en/grid-data/power-generation/generating-facilities#
A6: Amercoeur 1 R TGV | B6: Electrabel | F6: BE | G6: 451 | H6: Natural gas | I6: Combined cycle | N6: 50.43004 | P6: 4.39518 | Q6: 22WAMERCO000010Y | R6: Fossil fuels | S6: Natural gas | W6: https://www.elia.be/en/grid-data/power-generation/generating-facilities#
A7: AWIRS 4 | B7: Electrabel | F7: BE | G7: 95 | H7: Biomass and biogas | I7: Steam turbine | N7: 50.58508 | P7: 5.41886 | R7: Renewable energy | S7: Bioenergy | T7: Biomass and biogas | W7: https://www.elia.be/en/grid-data/power-generation/generating-facilities#
A8: BEERSE TJ | B8: Electrabel | F8: BE | G8: 32 | H8: Oil | I8: Gas turbine | R8: Fossil fuels | S8: Oil | W8: https://www.elia.be/en/grid-data/power-generation/generating-facilities#
A9: Beveren Ineos Phenolchemie | B9: Electrabel | F9: BE | G9: 23.8 | H9: Natural gas | K9: Yes | M9: CHP/IPP | R9: Fossil fuels | S9: Natural gas | W9: https://www.elia.be/en/grid-data/power-generation/generating-facilities#
A10: BUTGENBACH | B10: Electrabel | F10: BE | G10: 1.8 | H10: Hydro | R10: Renewable energy | S10: Hydro | W10: https://www.elia.be/en/grid-data/power-generation/generating-facilities#
A11: CIERREUX TJ | B11: Electrabel | F11: BE | G11: 18 | H11: Oil | I11: Gas turbine | R11: Fossil fuels | S11: Oil | W11: https://www.elia.be/en/grid-data/power-generation/generating-facilities#
A12: COO I T | B12: Electrabel | F12: BE | G12: 474 | H12: Hydro | N12: 50.38254 | P12: 5.84414 | Q12: 22WCOOXIX000067T | R12: Renewable energy | S12: Hydro | V12: Basin | W12: https://www.elia.be/en/grid-data/power-generation/generating-facilities#
A13: COO II T | B13: Electrabel | F13: BE | G13: 690 | H13: Hydro | N13: 50.38254 | P13: 5.84414 | Q13: 22WCOOXII000070C | R13: Renewable energy | S13: Hydro | V13: Basin | W13: https://www.elia.be/en/grid-data/power-generation/generating-facilities#
A14: DOEL 1 | B14: Electrabel | F14: BE | G14: 445 | H14: Nuclear | I14: Steam turbine | N14: 51.32481 | P14: 4.25889 | Q14: 22WDOELX1000076X | R14: Nuclear | W14: https://www.elia.be/en/grid-data/power-generation/generating-facilities#
A15: DOEL 2 | B15: Electrabel | F15: BE | G15: 433 | H15: Nuclear | I15: Steam turbine | N15: 51.32481 | P15: 4.25889 | Q15: 22WDOELX2000077N | R15: Nuclear | W15: https://www.elia.be/en/grid-data/power-generation/generating-facilities#
A16: DOEL 3 | B16: Electrabel | F16: BE | G16: 1006 | H16: Nuclear | I16: Steam turbine | N16: 51.32481 | P16: 4.25889 | Q16: 22WDOELX3000078D | R16: Nuclear | W16: https://www.elia.be/en/grid-data/power-generation/generating-facilities#
A17: DOEL 4 | B17: Electrabel | F17: BE | G17: 1039 | H17: Nuclear | I17: Steam turbine | N17: 51.32481 | P17: 4.25889 | Q17: 22WDOELX40000793 | R17: Nuclear | W17: https://www.elia.be/en/grid-data/power-generation/generating-facilities#
A18: DROGENBOS DM 51 | B18: Electrabel | F18: BE | G18: 2.5 | H18: Oil | N18: 50.80244 | P18: 4.30072 | R18: Fossil fuels | S18: Oil | V18: NoMetering | W18: https://www.elia.be/en/grid-data/power-generation/generating-facilities#
A19: DROGENBOS DM 52 | B19: Electrabel | F19: BE | G19: 2.5 | H19: Oil | N19: 50.80244 | P19: 4.30072 | R19: Fossil fuels | S19: Oil | V19: NoMetering | W19: https://www.elia.be/en/grid-data/power-generation/generating-facilities#
A20: DROGENBOS GT1 | B20: Electrabel | F20: BE | G20: 150 | H20: Natural gas | I20: Gas turbine | R20: Fossil fuels | S20: Natural gas | W20: https://www.elia.be/en/grid-data/power-generation/generating-facilities#
A21: DROGENBOS GT2 | B21: Electrabel | F21: BE | G21: 150 | H21: Natural gas | I21: Gas turbine | R21: Fossil fuels | S21: Natural gas | W21: https://www.elia.be/en/grid-data/power-generation/generating-facilities#
A22: DROGENBOS ST | B22: Electrabel | F22: BE | G22: 160 | H22: Natural gas | I22: Steam turbine | R22: Fossil fuels | S22: Natural gas | W22: https://www.elia.be/en/grid-data/power-generation/generating-facilities#
A23: HERDERSBRUG STEG | B23: Electrabel | F23: BE | G23: 465 | H23: Natural gas | I23: Combined cycle | N23: 51.26307 | P23: 3.21121 | Q23: 22WHERDER0001288 | R23: Fossil fuels | S23: Natural gas | W23: https://www.elia.be/en/grid-data/power-generation/generating-facilities#
A24: IXELLES TJ | B24: Electrabel | F24: BE | G24: 18 | H24: Oil | I24: Gas turbine | R24: Fossil fuels | S24: Oil | W24: https://www.elia.be/en/grid-data/power-generation/generating-facilities#
A25: La Vierre | B25: Electrabel | F25: BE | G25: 1.9 | H25: Hydro | R25: Renewable energy | S25: Hydro | W25: https://www.elia.be/en/grid-data/power-generation/generating-facilities#
A26: Lanaken Sappi | B26: Electrabel | F26: BE | G26: 43 | H26: Natural gas | K26: Yes | M26: CHP/IPP | R26: Fossil fuels | S26: Natural gas | W26: https://www.elia.be/en/grid-data/power-generation/generating-facilities#
A27: LANGERBRUGGE STORA ST 1 | B27: Electrabel | F27: BE | G27: 11 | H27: Non-renewable waste | I27: Steam turbine | K27: Yes | M27: CHP/IPP | R27: Fossil fuels | S27: Non-renewable waste | W27: https://www.elia.be/en/grid-data/power-generation/generating-facilities#
A28: LANGERBRUGGE STORA ST 2 | B28: Electrabel | F28: BE | G28: 44.7 | H28: Non-renewable waste | I28: Steam turbine | K28: Yes | M28: CHP/IPP | R28: Fossil fuels | S28: Non-renewable waste | W28: https://www.elia.be/en/grid-data/power-generation/generating-facilities#
A29: Lillo Degussa GT1 | B29: Electrabel | F29: BE | G29: 43 | H29: Natural gas | I29: Gas turbine | K29: Yes | M29: CHP/IPP | R29: Fossil fuels | S29: Natural gas | W29: https://www.elia.be/en/grid-data/power-generation/generating-facilities#
A30: Lillo Degussa GT2 | B30: Electrabel | F30: BE | G30: 32 | H30: Natural gas | I30: Gas turbine | K30: Yes | M30: CHP/IPP | R30: Fossil fuels | S30: Natural gas | W30: https://www.elia.be/en/grid-data/power-generation/generating-facilities#
A31: Lillo Degussa ST | B31: Electrabel | F31: BE | G31: 10 | H31: Natural gas | I31: Steam turbine | K31: Yes | M31: CHP/IPP | R31: Fossil fuels | S31: Natural gas | W31: https://www.elia.be/en/grid-data/power-generation/generating-facilities#
A32: Noordschote TJ | B32: Electrabel | F32: BE | G32: 18 | H32: Oil | I32: Gas turbine | R32: Fossil fuels | S32: Oil | W32: https://www.elia.be/en/grid-data/power-generation/generating-facilities#
A33: Oorderen Bayer | B33: Electrabel | F33: BE | G33: 43 | H33: Natural gas | K33: Yes | M33: CHP/IPP | R33: Fossil fuels | S33: Natural gas | W33: https://www.elia.be/en/grid-data/power-generation/generating-facilities#
A34: Oud-Lillo Monsanto | B34: Electrabel | F34: BE | G34: 43 | H34: Natural gas | K34: Yes | M34: CHP/IPP | R34: Fossil fuels | S34: Natural gas | W34: https://www.elia.be/en/grid-data/power-generation/generating-facilities#
A35: RODENHUIZE 4 | B35: Electrabel | F35: BE | G35: 268 | H35: Biomass and biogas | I35: Steam turbine | N35: 51.13421 | P35: 3.77598 | Q35: 22WRODENH000213L | R35: Renewable energy | S35: Bioenergy | T35: Biomass and biogas | W35: https://www.elia.be/en/grid-data/power-generation/generating-facilities#
A36: SAINT-GHISLAIN STEG | B36: Electrabel | F36: BE | G36: 350 | H36: Natural gas | I36: Combined cycle | N36: 50.47167 | P36: 3.82521 | Q36: 22WSAINT-000221B | R36: Fossil fuels | S36: Natural gas | W36: https://www.elia.be/en/grid-data/power-generation/generating-facilities#
A37: Schaerbeek Siomab ST1 | B37: Electrabel | F37: BE | G37: 15 | H37: Non-renewable waste | I37: Steam turbine | R37: Fossil fuels | S37: Non-renewable waste | W37: https://www.elia.be/en/grid-data/power-generation/generating-facilities#
A38: Schaerbeek Siomab ST2 | B38: Electrabel | F38: BE | G38: 15 | H38: Non-renewable waste | I38: Steam turbine | R38: Fossil fuels | S38: Non-renewable waste | W38: https://www.elia.be/en/grid-data/power-generation/generating-facilities#
A39: Schaerbeek Siomab ST3 | B39: Electrabel | F39: BE | G39: 15 | H39: Non-renewable waste | I39: Steam turbine | R39: Fossil fuels | S39: Non-renewable waste | W39: https://www.elia.be/en/grid-data/power-generation/generating-facilities#
A40: Scheldelaan Exxonmobil | B40: Electrabel | F40: BE | G40: 140 | H40: Natural gas | K40: Yes | M40: CHP/IPP | Q40: 22WSCHELD0002261 | R40: Fossil fuels | S40: Natural gas | W40: https://www.elia.be/en/grid-data/power-generation/generating-facilities#
A41: TIHANGE 1N | B41: Electrabel | F41: BE | G41: 481 | H41: Nuclear | I41: Steam turbine | N41: 50.53464 | P41: 5.27121 | Q41: 22WTIHANG000239G | R41: Nuclear | W41: https://www.elia.be/en/grid-data/power-generation/generating-facilities#
A42: TIHANGE 1S | B42: Electrabel | F42: BE | G42: 481 | H42: Nuclear | I42: Steam turbine | N42: 50.53464 | P42: 5.27121 | Q42: 22WTIHANG000240V | R42: Nuclear | W42: https://www.elia.be/en/grid-data/power-generation/generating-facilities#
A43: TIHANGE 2 | B43: Electrabel | F43: BE | G43: 1008 | H43: Nuclear | I43: Steam turbine | N43: 50.53464 | P43: 5.27121 | Q43: 22WTIHANG000241T | R43: Nuclear | W43: https://www.elia.be/en/grid-data/power-generation/generating-facilities#
A44: TIHANGE 3 | B44: Electrabel | F44: BE | G44: 1038 | H44: Nuclear | I44: Steam turbine | N44: 50.53464 | P44: 5.27121 | Q44: 22WTIHANG000242R | R44: Nuclear | W44: https://www.elia.be/en/grid-data/power-generation/generating-facilities#
A45: Turon TJ | B45: Electrabel | F45: BE | G45: 18.6 | H45: Oil | I45: Gas turbine | R45: Fossil fuels | S45: Oil | W45: https://www.elia.be/en/grid-data/power-generation/generating-facilities#
A46: VILVOORDE GT | B46: Electrabel | F46: BE | G46: 255 | H46: Natural gas | I46: Gas turbine | R46: Fossil fuels | S46: Natural gas | W46: https://www.elia.be/en/grid-data/power-generation/generating-facilities#
A47: Wilmarsdonk Total GT1 | B47: Electrabel | F47: BE | G47: 43 | H47: Natural gas | I47: Gas turbine | K47: Yes | M47: CHP/IPP | R47: Fossil fuels | S47: Natural gas | W47: https://www.elia.be/en/grid-data/power-generation/generating-facilities#
A48: Wilmarsdonk Total GT2 | B48: Electrabel | F48: BE | G48: 43 | H48: Natural gas | I48: Gas turbine | K48: Yes | M48: CHP/IPP | R48: Fossil fuels | S48: Natural gas | W48: https://www.elia.be/en/grid-data/power-generation/generating-facilities#
A49: Wilmarsdonk Total GT3 | B49: Electrabel | F49: BE | G49: 43 | H49: Natural gas | I49: Gas turbine | K49: Yes | M49: CHP/IPP | R49: Fossil fuels | S49: Natural gas | W49: https://www.elia.be/en/grid-data/power-generation/generating-facilities#
A50: Wilrijk Isvag | B50: Electrabel | F50: BE | G50: 12 | H50: Non-renewable waste | R50: Fossil fuels | S50: Non-renewable waste | W50: https://www.elia.be/en/grid-data/power-generation/generating-facilities#
A51: Zandvliet Power | B51: Electrabel | F51: BE | G51: 386.2 | H51: Natural gas | I51: Combined cycle | N51: 51.36977 | P51: 4.26667 | Q51: 22WZANDVL000255D | R51: Fossil fuels | S51: Natural gas | W51: https://www.elia.be/en/grid-data/power-generation/generating-facilities#
A52: Zedelgem TJ | B52: Electrabel | F52: BE | G52: 18 | H52: Oil | I52: Gas turbine | R52: Fossil fuels | S52: Oil | W52: https://www.elia.be/en/grid-data/power-generation/generating-facilities#
A53: Zeebrugge 2 Fluxys | B53: Electrabel | F53: BE | G53: 40 | H53: Natural gas | K53: Yes | M53: CHP/IPP | R53: Fossil fuels | S53: Natural gas | W53: https://www.elia.be/en/grid-data/power-generation/generating-facilities#
A54: Zeebrugge TJ | B54: Electrabel | F54: BE | G54: 18 | H54: Oil | I54: Gas turbine | R54: Fossil fuels | S54: Oil | W54: https://www.elia.be/en/grid-data/power-generation/generating-facilities#
A55: Zelzate 2 Knippegroen | B55: Electrabel | F55: BE | G55: 315 | H55: Mixed fossil fuels | I55: Steam turbine | N55: 51.15861 | P55: 3.80746 | Q55: 22WZELZAT0002618 | R55: Fossil fuels | S55: Mixed fossil fuels | W55: https://www.elia.be/en/grid-data/power-generation/generating-facilities#
A56: Zelzate TJ | B56: Electrabel | F56: BE | G56: 18 | H56: Oil | I56: Gas turbine | N56: 51.15879 | P56: 3.80815 | Q56: 22WZELZAT0002618 | R56: Fossil fuels | S56: Oil | W56: https://www.elia.be/en/grid-data/power-generation/generating-facilities#
A57: Zwijndrecht Lanxess GT | B57: Electrabel | F57: BE | G57: 43 | H57: Natural gas | I57: Gas turbine | K57: Yes | M57: CHP/IPP | R57: Fossil fuels | S57: Natural gas | W57: https://www.elia.be/en/grid-data/power-generation/generating-facilities#
A58: Zwijndrecht Lanxess ST | B58: Electrabel | F58: BE | G58: 15 | H58: Natural gas | I58: Steam turbine | K58: Yes | M58: CHP/IPP | R58: Fossil fuels | S58: Natural gas | W58: https://www.elia.be/en/grid-data/power-generation/generating-facilities#
A59: Electrawinds biomassa Oostende | B59: Electrawinds Distributie | F59: BE | G59: 18 | H59: Non-renewable waste | K59: Yes | M59: CHP/IPP | R59: Fossil fuels | S59: Non-renewable waste | W59: https://www.elia.be/en/grid-data/power-generation/generating-facilities#
A60: Greenpower Oostende | B60: Electrawinds Distributie | F60: BE | G60: 20 | H60: Non-renewable waste | R60: Fossil fuels | S60: Non-renewable waste | W60: https://www.elia.be/en/grid-data/power-generation/generating-facilities#
A61: Eurosilo | B61: Lampiris | F61: BE | G61: 12.9 | H61: Natural gas | K61: Yes | M61: CHP/IPP | R61: Fossil fuels | S61: Natural gas | W61: https://www.elia.be/en/grid-data/power-generation/generating-facilities#
A62: Incinerateur THUMAIDE (IPALLE) | B62: Lampiris | F62: BE | G62: 34 | H62: Non-renewable waste | R62: Fossil fuels | S62: Non-renewable waste | W62: https://www.elia.be/en/grid-data/power-generation/generating-facilities#
A63: Intradel Herstal | B63: Lampiris | F63: BE | G63: 34 | H63: Non-renewable waste | R63: Fossil fuels | S63: Non-renewable waste | W63: https://www.elia.be/en/grid-data/power-generation/generating-facilities#
A64: IVBO | B64: Lampiris | F64: BE | G64: 16 | H64: Non-renewable waste | R64: Fossil fuels | S64: Non-renewable waste | W64: https://www.elia.be/en/grid-data/power-generation/generating-facilities#
A65: PLATE-TAILLE T | B65: Lampiris | F65: BE | G65: 144 | H65: Hydro | Q65: 22WPLATEX000208N | R65: Renewable energy | S65: Hydro | V65: Basin | W65: https://www.elia.be/en/grid-data/power-generation/generating-facilities#
A66: ANGLEUR TG 41 | B66: Luminus | F66: BE | G66: 64 | H66: Natural gas | I66: Gas turbine | N66: 50.61775 | P66: 5.58267 | R66: Fossil fuels | S66: Natural gas | W66: https://www.elia.be/en/grid-data/power-generation/generating-facilities#
A67: ANGLEUR TG 42 | B67: Luminus | F67: BE | G67: 64 | H67: Natural gas | I67: Gas turbine | N67: 50.61775 | P67: 5.58267 | R67: Fossil fuels | S67: Natural gas | W67: https://www.elia.be/en/grid-data/power-generation/generating-facilities#
A68: ANGLEUR TG31 | B68: Luminus | F68: BE | G68: 25 | H68: Natural gas | R68: Fossil fuels | S68: Natural gas | W68: https://www.elia.be/en/grid-data/power-generation/generating-facilities#
A69: ANGLEUR TG32 | B69: Luminus | F69: BE | G69: 25 | H69: Natural gas | R69: Fossil fuels | S69: Natural gas | W69: https://www.elia.be/en/grid-data/power-generation/generating-facilities#
A70: Beveren 2 Indaver | B70: Luminus | F70: BE | G70: 21 | H70: Non-renewable waste | R70: Fossil fuels | S70: Non-renewable waste | W70: https://www.elia.be/en/grid-data/power-generation/generating-facilities#
A71: Beveren 3 Indaver | B71: Luminus | F71: BE | G71: 24 | H71: Non-renewable waste | R71: Fossil fuels | S71: Non-renewable waste | W71: https://www.elia.be/en/grid-data/power-generation/generating-facilities#
A72: Beveren Sleco | B72: Luminus | F72: BE | G72: 41 | H72: Non-renewable waste | R72: Fossil fuels | S72: Non-renewable waste | W72: https://www.elia.be/en/grid-data/power-generation/generating-facilities#
A73: EDF Luminus Izegem WKK | B73: Luminus | F73: BE | G73: 20 | H73: Natural gas | K73: Yes | M73: CHP/IPP | R73: Fossil fuels | S73: Natural gas | W73: https://www.elia.be/en/grid-data/power-generation/generating-facilities#
A74: EDF Luminus Seraing GT1 | B74: Luminus | F74: BE | G74: 150 | H74: Natural gas | I74: Gas turbine | R74: Fossil fuels | S74: Natural gas | W74: https://www.elia.be/en/grid-data/power-generation/generating-facilities#
A75: EDF Luminus Seraing GT2 | B75: Luminus | F75: BE | G75: 150 | H75: Natural gas | I75: Gas turbine | R75: Fossil fuels | S75: Natural gas | W75: https://www.elia.be/en/grid-data/power-generation/generating-facilities#
A76: HAM31 | B76: Luminus | F76: BE | G76: 58 | H76: Natural gas | I76: Gas turbine | N76: 51.05942 | P76: 3.73646 | R76: Fossil fuels | S76: Natural gas | W76: https://www.elia.be/en/grid-data/power-generation/generating-facilities#
A77: HAM32 | B77: Luminus | F77: BE | G77: 58 | H77: Natural gas | I77: Gas turbine | N77: 51.05942 | P77: 3.73646 | R77: Fossil fuels | S77: Natural gas | W77: https://www.elia.be/en/grid-data/power-generation/generating-facilities#
A78: HU AMPSIN-NEUVILLE | B78: Luminus | F78: BE | G78: 9.9 | H78: Hydro | N78: 50.53381 | P78: 5.29636 | R78: Renewable energy | S78: Hydro | W78: https://www.elia.be/en/grid-data/power-generation/generating-facilities#
A79: HU ANDENNE | B79: Luminus | F79: BE | G79: 9 | H79: Hydro | N79: 50.49179 | P79: 5.06975 | R79: Renewable energy | S79: Hydro | W79: https://www.elia.be/en/grid-data/power-generation/generating-facilities#
A80: HU FLORIFFOUX | B80: Luminus | F80: BE | G80: 0.8 | H80: Hydro | N80: 50.44663 | P80: 4.77389 | R80: Renewable energy | S80: Hydro | V80: NoMetering | W80: https://www.elia.be/en/grid-data/power-generation/generating-facilities#
A81: HU GRAND-MALADES | B81: Luminus | F81: BE | G81: 5 | H81: Hydro | N81: 50.46595 | P81: 4.89928 | R81: Renewable energy | S81: Hydro | W81: https://www.elia.be/en/grid-data/power-generation/generating-facilities#
A82: HU IVOZ-RAMET | B82: Luminus | F82: BE | G82: 10 | H82: Hydro | N82: 50.59349 | P82: 5.46137 | R82: Renewable energy | S82: Hydro | W82: https://www.elia.be/en/grid-data/power-generation/generating-facilities#
A83: HU LIXHE | B83: Luminus | F83: BE | G83: 20 | H83: Hydro | N83: 50.75178 | P83: 5.6878 | R83: Renewable energy | S83: Hydro | W83: https://www.elia.be/en/grid-data/power-generation/generating-facilities#
A84: HU MONSIN | B84: Luminus | F84: BE | G84: 19.7 | H84: Hydro | N84: 50.65317 | P84: 5.63137 | R84: Renewable energy | S84: Hydro | W84: https://www.elia.be/en/grid-data/power-generation/generating-facilities#
A85: Jemeppe-sur-Sambre GT1 | B85: Luminus | F85: BE | G85: 48 | H85: Natural gas | I85: Gas turbine | N85: 50.44746 | P85: 4.66339 | R85: Fossil fuels | S85: Natural gas | W85: https://www.elia.be/en/grid-data/power-generation/generating-facilities#
A86: Jemeppe-sur-Sambre GT2 | B86: Luminus | F86: BE | G86: 48 | H86: Natural gas | I86: Gas turbine | N86: 50.44746 | P86: 4.66339 | R86: Fossil fuels | S86: Natural gas | W86: https://www.elia.be/en/grid-data/power-generation/generating-facilities#
A87: Jemeppe-sur-Sambre ST | B87: Luminus | F87: BE | G87: 10 | H87: Natural gas | I87: Steam turbine | N87: 50.44746 | P87: 4.66339 | R87: Fossil fuels | S87: Natural gas | W87: https://www.elia.be/en/grid-data/power-generation/generating-facilities#
A88: RINGVAART STEG | B88: Luminus | F88: BE | G88: 385 | H88: Natural gas | I88: Combined cycle | N88: 51.10496 | P88: 3.72567 | Q88: 22WRINGVA000209C | R88: Fossil fuels | S88: Natural gas | W88: https://www.elia.be/en/grid-data/power-generation/generating-facilities#
A89: SERAING TV | B89: Luminus | F89: BE | G89: 170 | H89: Natural gas | R89: Fossil fuels | S89: Natural gas | W89: https://www.elia.be/en/grid-data/power-generation/generating-facilities#
A90: Biostoom Oostende | B90: RWE Supply & Trading | F90: BE | G90: 19.4 | H90: Non-renewable waste | I90: Combined cycle | R90: Fossil fuels | S90: Non-renewable waste | W90: https://www.elia.be/en/grid-data/power-generation/generating-facilities#
A91: INESCO WKK | B91: RWE Supply & Trading | F91: BE | G91: 138 | H91: Natural gas | I91: Combined cycle | K91: Yes | M91: CHP/IPP | N91: 51.24256 | P91: 4.32481 | Q91: 22WINESCO000149P | R91: Fossil fuels | S91: Natural gas | W91: https://www.elia.be/en/grid-data/power-generation/generating-facilities#
A92: T-power Beringen | B92: T-Power | F92: BE | G92: 422 | H92: Natural gas | I92: Combined cycle | Q92: 22WT-POWE000244W | R92: Fossil fuels | S92: Natural gas | W92: https://www.elia.be/en/grid-data/power-generation/generating-facilities#
A93: AL-1 | B93: NUON | C93: Marketkant 12-10 | D93: 1341AK | E93: Almere | F93: NL | G93: 62 | H93: Natural gas | N93: 52.38811 | P93: 5.2154 | R93: Fossil fuels | S93: Natural gas | W93: https://www.tennet.org/english/operational_management/export_data.aspx
A94: AL-2 | B94: NUON | C94: Markerkant 12-10 | D94: 1341AK | E94: Almere | F94: NL | G94: 55 | H94: Natural gas | N94: 52.38811 | P94: 5.2154 | R94: Fossil fuels | S94: Natural gas | W94: https://www.tennet.org/english/operational_management/export_data.aspx
A95: Amercentrale (A8) | B95: ESSENT ENERGY TRADING B.V. | C95: Amerweg . | D95: 4931NC | E95: Geertruidenberg | F95: NL | G95: 645 | H95: Hard coal | I95: Steam turbine | N95: 51.70838 | P95: 4.84381 | Q95: 49W000000000070Z | R95: Fossil fuels | S95: Hard coal | W95: https://www.tennet.org/english/operational_management/export_data.aspx
A96: Amercentrale (A9) | B96: ESSENT ENERGY TRADING B.V. | C96: Amerweg . | D96: 4931NC | E96: Geertruidenberg | F96: NL | G96: 640 | H96: Hard coal | I96: Steam turbine | N96: 51.70838 | P96: 4.84381 | Q96: 49W000000000070Z | R96: Fossil fuels | S96: Hard coal | W96: https://www.tennet.org/english/operational_management/export_data.aspx
A97: Amylum | B97: AMYLUM NEDERLAND B.V. | C97: Lagedijk 5 | D97: 1541KA | E97: Koog aan de Zaan | F97: NL | G97: 7 | H97: Natural gas | N97: 52.46552 | P97: 4.81361 | R97: Fossil fuels | S97: Natural gas | W97: https://www.tennet.org/english/operational_management/export_data.aspx
A98: BOZ | B98: ESSENT ENERGY TRADING B.V. | C98: Moervaart 1 | D98: 4622RR | E98: Bergen op Zoom | F98: NL | G98: 33 | H98: Natural gas | N98: 51.50555 | P98: 4.33998 | R98: Fossil fuels | S98: Natural gas | W98: https://www.tennet.org/english/operational_management/export_data.aspx
A99: Borssele 30 | B99: DELTA ENERGY B.V. | C99: Zeedijk 32 | D99: 4454PM | E99: Borssele | F99: NL | G99: 492 | H99: Nuclear | I99: Steam turbine | N99: 51.43148 | P99: 3.71871 | Q99: 49W000000000054X | R99: Nuclear | W99: https://www.tennet.org/english/operational_management/export_data.aspx
A100: CUIJK | B100: ESSENT ENERGY TRADING B.V. | C100: Lange Ooijen 31 | D100: 5433NG | E100: Katwijk (NB) | F100: NL | G100: 25 | H100: Hard coal | I100: Steam turbine | N100: 51.75381 | P100: 5.8528 | R100: Fossil fuels | S100: Hard coal | W100: https://www.tennet.org/english/operational_management/export_data.aspx
...

Sheet Final table
G5: Final Table
D21: Questuions:
D22: Are these technologies covering denmarks current state of none renewables?
D23: Or should we assume that these sources are sufficient?
D24: How do we derive marginal cost from fixed and variable operating costs? | G24: > use variable cost | H24: Fixed = annual mainteinance
D25: Need marginal fuel prices?
D26: Add co2 emisisons? How would we include this in the model if we want to track co2 emission?
D27: We can also include start up time, but it might not be relevant in our context?
D28: How to hanlde mixed fossil fuels?
